srttools/__init__.py
srttools/_astropy_init.py
srttools/calibration.py
srttools/conftest.py
srttools/convert.py
srttools/destripe.py
srttools/fit.py
srttools/global_fit.py
srttools/histograms.py
srttools/imager.py
srttools/inspect_observations.py
srttools/interactive_filter.py
srttools/io.py
srttools/logging.py
srttools/opacity.py
srttools/parse_acs_logs.py
srttools/read_config.py
srttools/rfistat.py
srttools/scan.py
srttools/simulate.py
srttools/utils.py
srttools/version.py
srttools/converters/__init__.py
srttools/converters/classfits.py
srttools/converters/mbfits.py
srttools/converters/sdfits.py
srttools/data/scan_template.fits
srttools/data/calibrators/3C123.ini
srttools/data/calibrators/3C138.ini
srttools/data/calibrators/3C147.ini
srttools/data/calibrators/3C196.ini
srttools/data/calibrators/3C286.ini
srttools/data/calibrators/3C295.ini
srttools/data/calibrators/3C48.ini
srttools/data/calibrators/DummyCal.ini
srttools/data/calibrators/DummyCal2.ini
srttools/data/calibrators/NGC7027.ini
srttools/data/calibrators/__init__.py
srttools/data/calibrators/coeff2.csv
srttools/data/calibrators/coeff2.tex
srttools/data/calibrators/parse_tex_table.py
srttools/data/calibrators/1211.1300v1/PaperNoPol.tex
srttools/data/calibrators/1211.1300v1/coeff.csv
srttools/data/calibrators/1211.1300v1/coeff.tex
srttools/data/calibrators/1211.1300v1/coeff.txt
srttools/data/calibrators/1211.1300v1/table1.csv
srttools/data/calibrators/1211.1300v1/table1.numbers
srttools/data/calibrators/1211.1300v1/table1.txt
srttools/data/mbfits_template/FLASH460L-XFFTS-FEBEPAR.fits
srttools/data/mbfits_template/GROUPING.fits
srttools/data/mbfits_template/SCAN.fits
srttools/data/mbfits_template/1/FLASH460L-XFFTS-ARRAYDATA-1.fits
srttools/data/mbfits_template/1/FLASH460L-XFFTS-ARRAYDATA-2.fits
srttools/data/mbfits_template/1/FLASH460L-XFFTS-ARRAYDATA-3.fits
srttools/data/mbfits_template/1/FLASH460L-XFFTS-ARRAYDATA-4.fits
srttools/data/mbfits_template/1/FLASH460L-XFFTS-DATAPAR.fits
srttools-0.7.2.dist-info/METADATA
srttools-0.7.2.dist-info/WHEEL
srttools-0.7.2.dist-info/entry_points.txt
srttools-0.7.2.dist-info/top_level.txt
srttools-0.7.2.dist-info/RECORD
